{"0": "handleError", "1": "Password", "2": "LabTestsRepository", "3": "main", "4": "Result", "5": "config.go", "6": "Report", "7": "ListVisit", "8": "Order", "9": "Patient", "10": "GetProfileDetails", "11": "Doctor", "12": "LabSettings", "13": "labTests.go", "14": "DB", "15": "20260707080505_create_departments_table.sql", "16": "LoginResponse", "17": "20260710073046_visit_result_table.sql", "18": "20260702101734_create_user_table.sql", "19": "20260709063003_other_users_table.sql", "20": "20260713074207_report_table.sql", "21": "doctor.go", "22": "lab.go", "23": "labTests.go", "24": "orderItem.go", "25": "patient.go", "26": "profile.go", "27": "report.go", "28": "result.go", "29": "role.go", "30": "users.go", "31": "visit.go", "32": "CreateRole", "33": "20260702094601_create_role_table.sql", "34": "20260706113407_create_lab_settings.sql", "35": "errors.go", "36": "github.com/jenish-brainztechs/go-backend"}